inaccel/coral/__init__.py
inaccel/coral/_library.py
inaccel/coral/_rpc.py
inaccel/coral/_shm.py
inaccel/coral/native/libcoral-api.so
coral_api-2.5.0.dist-info/LICENSE
coral_api-2.5.0.dist-info/METADATA
coral_api-2.5.0.dist-info/NOTICE
coral_api-2.5.0.dist-info/WHEEL
coral_api-2.5.0.dist-info/top_level.txt
coral_api-2.5.0.dist-info/RECORD
