Metadata-Version: 2.1
Name: coral-api
Version: 2.5.0
Summary: Enterprise-Grade Accelerator Orchestration
Home-page: https://inaccel.com
Author: InAccel
Author-email: info@inaccel.com
License: Apache-2.0
Keywords: InAccel,Coral,API
Platform: Linux
Classifier: Development Status :: 5 - Production/Stable
Classifier: License :: OSI Approved :: Apache Software License
Classifier: Operating System :: POSIX :: Linux
Classifier: Programming Language :: Python
Classifier: Programming Language :: Python :: 3
Classifier: Programming Language :: Python :: 3.8
Classifier: Programming Language :: Python :: 3.9
Classifier: Programming Language :: Python :: 3.10
Classifier: Programming Language :: Python :: 3.11
Requires-Python: >=3.8
License-File: LICENSE
License-File: NOTICE
Requires-Dist: numpy-allocator >=1.2.0
